qgeneration/__init__.py
qgeneration/fields.py
qgeneration/functions.py
qgeneration/qfields.py
qgeneration/qrecords.py
qgeneration/records.py
qgeneration-0.1a3.dist-info/DESCRIPTION.rst
qgeneration-0.1a3.dist-info/METADATA
qgeneration-0.1a3.dist-info/RECORD
qgeneration-0.1a3.dist-info/WHEEL
qgeneration-0.1a3.dist-info/metadata.json
qgeneration-0.1a3.dist-info/top_level.txt
